django_plugin_whitenoise/__init__.py
django_plugin_whitenoise-0.1.2.dist-info/WHEEL
django_plugin_whitenoise-0.1.2.dist-info/entry_points.txt
django_plugin_whitenoise-0.1.2.dist-info/METADATA
django_plugin_whitenoise-0.1.2.dist-info/RECORD
